mcts/__init__.py
mcts/base/__init__.py
mcts/base/base.py
mcts/example/__init__.py
mcts/example/connectmnk.py
mcts/example/naughtsandcrosses.py
mcts/searcher/__init__.py
mcts/searcher/mcts.py
monte_carlo_tree_search-2.1.0.dist-info/licenses/LICENSE.txt
monte_carlo_tree_search-2.1.0.dist-info/METADATA
monte_carlo_tree_search-2.1.0.dist-info/WHEEL
monte_carlo_tree_search-2.1.0.dist-info/top_level.txt
monte_carlo_tree_search-2.1.0.dist-info/RECORD
