Metadata-Version: 2.4
Name: monte-carlo-tree-search
Version: 2.1.0
Summary: A simple package to allow users to run Monte Carlo Tree Search on any perfect information domain
Home-page: https://github.com/kstruempf/MCTS
Author: Paul Sinclair, Konstantin Strümpf and others
Author-email: k.struempf@icloud.com
License: MIT
Keywords: mcts,monte,carlo,tree,search
Classifier: Intended Audience :: Developers
Classifier: Intended Audience :: Education
Classifier: Intended Audience :: Science/Research
Classifier: License :: OSI Approved :: MIT License
Classifier: Operating System :: OS Independent
Classifier: Programming Language :: Python :: 2
Classifier: Programming Language :: Python :: 3
Classifier: Topic :: Scientific/Engineering
Classifier: Topic :: Scientific/Engineering :: Artificial Intelligence
Classifier: Topic :: Software Development
Classifier: Topic :: Software Development :: Libraries
Classifier: Topic :: Software Development :: Libraries :: Python Modules
License-File: LICENSE.txt
Dynamic: author
Dynamic: author-email
Dynamic: classifier
Dynamic: description
Dynamic: description-content-type
Dynamic: home-page
Dynamic: keywords
Dynamic: license
Dynamic: license-file
Dynamic: summary
